driconfig/__init__.py
driconfig-1.1.1.dist-info/METADATA
driconfig-1.1.1.dist-info/WHEEL
driconfig-1.1.1.dist-info/licenses/LICENSE
driconfig-1.1.1.dist-info/RECORD
