Metadata-Version: 2.4
Name: driconfig
Version: 1.1.1
Summary: Pydantic-ish YAML configuration management.
Project-URL: Homepage, https://dribia.github.io/driconfig
Project-URL: Repository, https://github.com/dribia/driconfig
Project-URL: Documentation, https://dribia.github.io/driconfig
Author-email: Dribia Data Research <code@dribia.com>
Maintainer-email: Dribia Data Research <code@dribia.com>
License-Expression: MIT
License-File: LICENSE
Classifier: Intended Audience :: Developers
Classifier: License :: OSI Approved :: MIT License
Classifier: Operating System :: OS Independent
Classifier: Programming Language :: Python
Classifier: Programming Language :: Python :: 3
Classifier: Programming Language :: Python :: 3 :: Only
Classifier: Programming Language :: Python :: 3.9
Classifier: Programming Language :: Python :: 3.10
Classifier: Programming Language :: Python :: 3.11
Classifier: Programming Language :: Python :: 3.12
Classifier: Programming Language :: Python :: 3.13
Classifier: Programming Language :: Python :: 3.14
Classifier: Topic :: Internet
Classifier: Topic :: Software Development
Classifier: Topic :: Software Development :: Libraries
Classifier: Topic :: Software Development :: Libraries :: Python Modules
Classifier: Typing :: Typed
Requires-Python: <3.15,>=3.9
Requires-Dist: pydantic-settings<3,>=2.0.1
Requires-Dist: pyyaml~=6.0
